rosbags/dataframe/__init__.py
rosbags/dataframe/dataframe.py
rosbags/dataframe/py.typed
rosbags_dataframe-0.10.1.dist-info/licenses/LICENSE.txt
rosbags_dataframe-0.10.1.dist-info/METADATA
rosbags_dataframe-0.10.1.dist-info/WHEEL
rosbags_dataframe-0.10.1.dist-info/top_level.txt
rosbags_dataframe-0.10.1.dist-info/RECORD
