Metadata-Version: 2.4
Name: rosbags-dataframe
Version: 0.10.1
Summary: Python library to convert ros message streams to pandas dataframes.
Author-email: Ternaris <team@ternaris.com>
License-Expression: Apache-2.0
Project-URL: Homepage, https://gitlab.com/ternaris/rosbags-dataframe
Project-URL: Documentation, https://ternaris.gitlab.io/rosbags-dataframe
Project-URL: Source, https://gitlab.com/ternaris/rosbags-dataframe
Project-URL: Issues, https://gitlab.com/ternaris/rosbags-dataframe/issues
Project-URL: Changelog, https://gitlab.com/ternaris/rosbags-dataframe/-/blob/master/CHANGES.rst
Keywords: conversion,dataframe,message,msg,pandas,ros,ros2,rosbag,rosbag1,rosbag2,rosbags,series
Classifier: Development Status :: 4 - Beta
Classifier: Programming Language :: Python
Classifier: Programming Language :: Python :: 3 :: Only
Classifier: Programming Language :: Python :: 3.10
Classifier: Programming Language :: Python :: 3.11
Classifier: Programming Language :: Python :: 3.12
Classifier: Programming Language :: Python :: 3.13
Classifier: Programming Language :: Python :: 3.14
Classifier: Topic :: Scientific/Engineering
Classifier: Typing :: Typed
Requires-Python: >=3.10
License-File: LICENSE.txt
Requires-Dist: pandas
Requires-Dist: rosbags>=0.9.20
Dynamic: license-file
